tjex/__init__.py
tjex/config.py
tjex/curses_helper.py
tjex/history.py
tjex/jq.py
tjex/json_table.py
tjex/kill_ring.py
tjex/logging.py
tjex/panel.py
tjex/point.py
tjex/resources/builtins.jq
tjex/table.py
tjex/table_panel.py
tjex/text_panel.py
tjex/tjex.py
tjex/utils.py
tjex-0.2.0.dist-info/licenses/LICENSE
tjex-0.2.0.dist-info/WHEEL
tjex-0.2.0.dist-info/entry_points.txt
tjex-0.2.0.dist-info/METADATA
tjex-0.2.0.dist-info/RECORD
