Metadata-Version: 2.4
Name: tjex
Version: 0.2.0
Summary: A Tabular Json Explorer
Author: Justin Knapheide
Author-email: Justin Knapheide <mail@jknapheide.de>
License-Expression: MIT
License-File: LICENSE
Requires-Dist: argcomplete
Requires-Python: >=3.12
Project-URL: Homepage, https://github.com/knapheide/tjex
Project-URL: Repository, https://github.com/knapheide/tjex
